src/__init__.py
src/__main__.py
src/assets/base.css
src/assets/code.css
src/assets/small.css
src/assets/whine.css
src/cli.py
src/constants/cf_tpl.mp
src/constants/cmd.mp
src/constants/const.mp
src/constants/lang/en.mp
src/globals.py
src/info.py
src/katex/bin/katex_v0.16.4_node16_x86_64-linux
src/katex/bin/katex_v0.16.4_node16_x86_64-mac
src/katex/bin/katex_v0.16.4_node16_x86_64-win.exe
src/katex/fonts/KaTeX_AMS-Regular.ttf
src/katex/fonts/KaTeX_AMS-Regular.woff
src/katex/fonts/KaTeX_AMS-Regular.woff2
src/katex/fonts/KaTeX_Caligraphic-Bold.ttf
src/katex/fonts/KaTeX_Caligraphic-Bold.woff
src/katex/fonts/KaTeX_Caligraphic-Bold.woff2
src/katex/fonts/KaTeX_Caligraphic-Regular.ttf
src/katex/fonts/KaTeX_Caligraphic-Regular.woff
src/katex/fonts/KaTeX_Caligraphic-Regular.woff2
src/katex/fonts/KaTeX_Fraktur-Bold.ttf
src/katex/fonts/KaTeX_Fraktur-Bold.woff
src/katex/fonts/KaTeX_Fraktur-Bold.woff2
src/katex/fonts/KaTeX_Fraktur-Regular.ttf
src/katex/fonts/KaTeX_Fraktur-Regular.woff
src/katex/fonts/KaTeX_Fraktur-Regular.woff2
src/katex/fonts/KaTeX_Main-Bold.ttf
src/katex/fonts/KaTeX_Main-Bold.woff
src/katex/fonts/KaTeX_Main-Bold.woff2
src/katex/fonts/KaTeX_Main-BoldItalic.ttf
src/katex/fonts/KaTeX_Main-BoldItalic.woff
src/katex/fonts/KaTeX_Main-BoldItalic.woff2
src/katex/fonts/KaTeX_Main-Italic.ttf
src/katex/fonts/KaTeX_Main-Italic.woff
src/katex/fonts/KaTeX_Main-Italic.woff2
src/katex/fonts/KaTeX_Main-Regular.ttf
src/katex/fonts/KaTeX_Main-Regular.woff
src/katex/fonts/KaTeX_Main-Regular.woff2
src/katex/fonts/KaTeX_Math-BoldItalic.ttf
src/katex/fonts/KaTeX_Math-BoldItalic.woff
src/katex/fonts/KaTeX_Math-BoldItalic.woff2
src/katex/fonts/KaTeX_Math-Italic.ttf
src/katex/fonts/KaTeX_Math-Italic.woff
src/katex/fonts/KaTeX_Math-Italic.woff2
src/katex/fonts/KaTeX_SansSerif-Bold.ttf
src/katex/fonts/KaTeX_SansSerif-Bold.woff
src/katex/fonts/KaTeX_SansSerif-Bold.woff2
src/katex/fonts/KaTeX_SansSerif-Italic.ttf
src/katex/fonts/KaTeX_SansSerif-Italic.woff
wh_m2p-0.0.1a0.dist-info/METADATA
wh_m2p-0.0.1a0.dist-info/WHEEL
wh_m2p-0.0.1a0.dist-info/entry_points.txt
wh_m2p-0.0.1a0.dist-info/RECORD
