Metadata-Version: 2.1
Name: wh-m2p
Version: 0.0.1a0
Summary: 
Home-page: https://m2p.whinyaan.xyz
License: MIT
Author: whitespace_negative
Author-email: whinyaan@protonmail.com
Maintainer: whitespace_negative
Maintainer-email: whinyaan@protonmail.com
Requires-Python: >=3.10,<4
Classifier: Development Status :: 2 - Pre-Alpha
Classifier: Environment :: Console
Classifier: Intended Audience :: Developers
Classifier: Intended Audience :: Education
Classifier: Intended Audience :: End Users/Desktop
Classifier: License :: OSI Approved :: MIT License
Classifier: Natural Language :: English
Classifier: Operating System :: OS Independent
Classifier: Programming Language :: Python :: 3
Classifier: Programming Language :: Python :: 3.10
Classifier: Programming Language :: Python :: 3.11
Classifier: Programming Language :: Python :: 3
Classifier: Topic :: Office/Business
Classifier: Topic :: Text Processing :: Markup :: Markdown
Classifier: Topic :: Utilities
Requires-Dist: arrow (>=1.2.3,<2.0.0)
Requires-Dist: click (>=8.1.3,<9.0.0)
Requires-Dist: markdown (>=3.4.3,<4.0.0)
Requires-Dist: msgpack (>=1.0.5,<2.0.0)
Requires-Dist: pypandoc (>=1.11,<2.0)
Requires-Dist: pyyaml (>=6.0,<7.0)
Requires-Dist: questionary (>=1.10.0,<2.0.0)
Requires-Dist: rich (>=13.3.3,<14.0.0)
Requires-Dist: tabulate (>=0.9.0,<0.10.0)
Requires-Dist: weasyprint (>=58.1,<59.0)
Requires-Dist: yachalk (>=0.1.5,<0.2.0)
Project-URL: Documentation, https://m2p.whinyaan.xyz
Project-URL: Repository, https://github.com/whinee/md2pdf
